awaredatetime/__init__.py
awaredatetime/config.py
awaredatetime-0.0.2.dist-info/DESCRIPTION.rst
awaredatetime-0.0.2.dist-info/METADATA
awaredatetime-0.0.2.dist-info/RECORD
awaredatetime-0.0.2.dist-info/WHEEL
awaredatetime-0.0.2.dist-info/metadata.json
awaredatetime-0.0.2.dist-info/top_level.txt
